djs3/__init__.py
djs3/apps.py
djs3/s3.py
djs3/storage.py
djs3-2021.10.11.dist-info/LICENSE
djs3-2021.10.11.dist-info/WHEEL
djs3-2021.10.11.dist-info/METADATA
djs3-2021.10.11.dist-info/RECORD
