Metadata-Version: 2.1
Name: djs3
Version: 2021.10.11
Summary: S3 in Django
License: MIT
Author: Atem18
Author-email: messer.kevin@gmail.com
Requires-Python: >=3.9,<4.0
Classifier: License :: OSI Approved :: MIT License
Classifier: Programming Language :: Python :: 3
Classifier: Programming Language :: Python :: 3.9
Requires-Dist: Django (>=3.2.8,<4.0.0)
Requires-Dist: boto3 (>=1.18.59,<2.0.0)
Requires-Dist: pydantic (>=1.8.2,<2.0.0)
